<?xml version="1.0" encoding="utf-8"?>
<resources>
    <style name="ShapeAppearance.DIPS.SmallComponent" parent="ShapeAppearance.MaterialComponents.SmallComponent">
        <item name="cornerFamily">rounded</item>
        <item name="cornerSize">10dp</item>  <!-- TODO: Use DesignSystem -->
    </style>

    <style name="ShapeAppearance.DIPS.MediumComponent" parent="ShapeAppearance.MaterialComponents.MediumComponent">
        <item name="cornerFamily">rounded</item>
        <item name="cornerSize">10dp</item>  <!-- TODO: Use DesignSystem -->
    </style>

    <style name="ShapeAppearance.DIPS.LargeComponent" parent="ShapeAppearance.MaterialComponents.LargeComponent">
        <item name="cornerFamily">rounded</item>
        <item name="cornerSize">10dp</item>  <!-- TODO: Use DesignSystem -->
    </style>
</resources>