<?xml version="1.0" encoding="utf-8"?>
<!--
Puls Design Tokens
Do not edit directly, this file is auto-generated
Generated: 2026-03-11T13:44:35.681Z
-->
<!-- Light mode -->
<resources>
    <color name="color_background_default">#F9FFFEFC</color> <!-- background-default -->
    <color name="color_surface_default">#FFFFFFFF</color> <!-- surface-default -->
    <color name="color_surface_information">#FCFFEFF5</color> <!-- surface-information -->
    <color name="color_surface_success">#D6FFE9FC</color> <!-- surface-success -->
    <color name="color_surface_warning">#CAFFFCF6</color> <!-- surface-warning -->
    <color name="color_surface_danger">#E5FFFCE9</color> <!-- surface-danger -->
    <color name="color_surface_subtle">#F0FFF9F5</color> <!-- surface-subtle -->
    <color name="color_surface_highlight">#FEFFFDF3</color> <!-- surface-highlight -->
    <color name="color_surface_default_hover">#E8FFF3ED</color> <!-- surface-default-hover -->
    <color name="color_surface_default_selected">#D0FFDED6</color> <!-- surface-default-selected -->
    <color name="color_surface_default_active">#D0FFDED6</color> <!-- surface-default-active -->
    <color name="color_surface_subtle_hover">#E8FFF3ED</color> <!-- surface-subtle-hover -->
    <color name="color_surface_subtle_active">#D0FFDED6</color> <!-- surface-subtle-active -->
    <color name="color_surface_subtle_selected">#D0FFDED6</color> <!-- surface-subtle-selected -->
    <color name="color_surface_neutral">#F0FFF9F5</color> <!-- surface-neutral -->
    <color name="color_surface_highlight_hover">#FCFFFAE4</color> <!-- surface-highlight-hover -->
    <color name="color_surface_highlight_active">#FAFFE4CC</color> <!-- surface-highlight-active -->
    <color name="color_surface_backdrop">#1A4D241E</color> <!-- surface-backdrop -->
    <color name="color_surface_disabled">#FFFFFFFF</color> <!-- surface-disabled -->
    <color name="color_surface_readonly">#F9FFFEFC</color> <!-- surface-readonly -->
    <color name="color_fill_default">#FFFFFFFF</color> <!-- fill-default -->
    <color name="color_fill_information">#FCFFEFF5</color> <!-- fill-information -->
    <color name="color_fill_success">#D6FFE9FC</color> <!-- fill-success -->
    <color name="color_fill_warning">#CAFFFCF6</color> <!-- fill-warning -->
    <color name="color_fill_danger">#E5FFFCE9</color> <!-- fill-danger -->
    <color name="color_fill_default_hover">#E8FFF3ED</color> <!-- fill-default-hover -->
    <color name="color_fill_default_active">#D0FFDED6</color> <!-- fill-default-active -->
    <color name="color_fill_default_selected">#D0FFDED6</color> <!-- fill-default-selected -->
    <color name="color_fill_button_ghost">#FF00FFFF</color> <!-- fill-button-ghost -->
    <color name="color_fill_button_disabled">#D0FFDED6</color> <!-- fill-button-disabled -->
    <color name="color_fill_button_ghost_hover">#E8FFF3ED</color> <!-- fill-button-ghost-hover -->
    <color name="color_fill_button_ghost_active">#D0FFDED6</color> <!-- fill-button-ghost-active -->
    <color name="color_fill_input">#FFFFFFFF</color> <!-- fill-input -->
    <color name="color_fill_input_disabled">#FFFFFFFF</color> <!-- fill-input-disabled -->
    <color name="color_fill_input_readonly">#E8FFF3ED</color> <!-- fill-input-readonly -->
    <color name="color_fill_input_indicator">#56FF645C</color> <!-- fill-input-indicator -->
    <color name="color_fill_input_indicator_hover">#40FF4E46</color> <!-- fill-input-indicator-hover -->
    <color name="color_fill_neutral">#F0FFF9F5</color> <!-- fill-neutral -->
    <color name="color_fill_input_toggle">#84FF938A</color> <!-- fill-input-toggle -->
    <color name="color_fill_input_toggle_hover">#B5FFC4BC</color> <!-- fill-input-toggle-hover -->
    <color name="color_fill_input_toggle_selected">#A0FFC4E5</color> <!-- fill-input-toggle-selected -->
    <color name="color_fill_button_cta_active">#56FF645C</color> <!-- fill-button-cta-active -->
    <color name="color_fill_button_cta">#2CFF3831</color> <!-- fill-button-cta -->
    <color name="color_fill_button_cta_hover">#40FF4E46</color> <!-- fill-button-cta-hover -->
    <color name="color_fill_button">#FF00FFFF</color> <!-- fill-button -->
    <color name="color_fill_button_hover">#E8FFF3ED</color> <!-- fill-button-hover -->
    <color name="color_fill_button_active">#D0FFDED6</color> <!-- fill-button-active -->
    <color name="color_fill_button_danger">#03FFBA22</color> <!-- fill-button-danger -->
    <color name="color_fill_button_danger_hover">#16FFCF35</color> <!-- fill-button-danger-hover -->
    <color name="color_fill_button_danger_active">#39FFE957</color> <!-- fill-button-danger-active -->
    <color name="color_fill_highlight">#FAFFE4CC</color> <!-- fill-highlight -->
    <color name="color_fill_disabled">#B5FFC4BC</color> <!-- fill-disabled -->
    <color name="color_fill_input_indicator_readonly">#9CFFABA3</color> <!-- fill-input-indicator-readonly -->
    <color name="color_fill_success_hover">#A0FFC4E5</color> <!-- fill-success-hover -->
    <color name="color_fill_success_active">#82FFA9CB</color> <!-- fill-success-active -->
    <color name="color_fill_subtle">#F0FFF9F5</color> <!-- fill-subtle -->
    <color name="color_fill_inverted">#1AFF241E</color> <!-- fill-inverted -->
    <color name="color_fill_highlight_hover">#FAFFE4CC</color> <!-- fill-highlight-hover -->
    <color name="color_fill_highlight_active">#E2FFCBB2</color> <!-- fill-highlight-active -->
    <color name="color_fill_button_ghost_danger_active">#C5FFFCCE</color> <!-- fill-button-ghost-danger-active -->
    <color name="color_fill_button_ghost_danger_hover">#E5FFFCE9</color> <!-- fill-button-ghost-danger-hover -->
    <color name="color_fill_button_ghost_danger">#FF00FFFF</color> <!-- fill-button-ghost-danger -->
    <color name="color_text_default">#1AFF241E</color> <!-- text-default -->
    <color name="color_text_subtle">#56FF645C</color> <!-- text-subtle -->
    <color name="color_text_link">#9BFF355D</color> <!-- text-link -->
    <color name="color_text_link_hover">#49FF001C</color> <!-- text-link-hover -->
    <color name="color_text_on_fill_disabled">#FFFFFFFF</color> <!-- text-on-fill-disabled -->
    <color name="color_text_label">#1AFF241E</color> <!-- text-label -->
    <color name="color_text_input">#1AFF241E</color> <!-- text-input -->
    <color name="color_text_disabled">#B5FFC4BC</color> <!-- text-disabled -->
    <color name="color_text_link_neutral">#1AFF241E</color> <!-- text-link-neutral -->
    <color name="color_text_on_button">#1AFF241E</color> <!-- text-on-button -->
    <color name="color_text_readonly">#40FF4E46</color> <!-- text-readonly -->
    <color name="color_text_danger">#03FFBA22</color> <!-- text-danger -->
    <color name="color_text_on_button_inverted">#FFFFFFFF</color> <!-- text-on-button-inverted -->
    <color name="color_text_link_neutral_hover">#56FF645C</color> <!-- text-link-neutral-hover -->
    <color name="color_text_action">#9BFF355D</color> <!-- text-action -->
    <color name="color_icon_default">#1AFF241E</color> <!-- icon-default -->
    <color name="color_icon_subtle">#6CFF7B73</color> <!-- icon-subtle -->
    <color name="color_icon_link">#9BFF355D</color> <!-- icon-link -->
    <color name="color_icon_link_hover">#49FF001C</color> <!-- icon-link-hover -->
    <color name="color_icon_on_fill_success">#1AFF241E</color> <!-- icon-on-fill-success -->
    <color name="color_icon_danger">#03FFBA22</color> <!-- icon-danger -->
    <color name="color_icon_input">#40FF4E46</color> <!-- icon-input -->
    <color name="color_icon_on_fill_disabled">#FFFFFFFF</color> <!-- icon-on-fill-disabled -->
    <color name="color_icon_on_fill_success_hover">#FFFFFFFF</color> <!-- icon-on-fill-success-hover -->
    <color name="color_icon_disabled">#B5FFC4BC</color> <!-- icon-disabled -->
    <color name="color_icon_readonly">#40FF4E46</color> <!-- icon-readonly -->
    <color name="color_icon_link_neutral">#1AFF241E</color> <!-- icon-link-neutral -->
    <color name="color_icon_link_neutral_hover">#56FF645C</color> <!-- icon-link-neutral-hover -->
    <color name="color_icon_on_button">#1AFF241E</color> <!-- icon-on-button -->
    <color name="color_icon_on_button_inverted">#FFFFFFFF</color> <!-- icon-on-button-inverted -->
    <color name="color_icon_input_hover">#1AFF241E</color> <!-- icon-input-hover -->
    <color name="color_icon_input_active">#CEFF638D</color> <!-- icon-input-active -->
    <color name="color_icon_action">#9BFF355D</color> <!-- icon-action -->
    <color name="color_icon_default_hover">#56FF645C</color> <!-- icon-default-hover -->
    <color name="color_icon_success">#16FF4969</color> <!-- icon-success -->
    <color name="color_border_default">#B5FFC4BC</color> <!-- border-default -->
    <color name="color_border_subtle">#D0FFDED6</color> <!-- border-subtle -->
    <color name="color_border_focus_ring">#CEFF638D</color> <!-- border-focus-ring -->
    <color name="color_border_button">#6CFF7B73</color> <!-- border-button -->
    <color name="color_border_default_hover">#6CFF7B73</color> <!-- border-default-hover -->
    <color name="color_border_input">#40FF4E46</color> <!-- border-input -->
    <color name="color_border_input_hover">#1AFF241E</color> <!-- border-input-hover -->
    <color name="color_border_input_active">#CEFF638D</color> <!-- border-input-active -->
    <color name="color_border_input_disabled">#B5FFC4BC</color> <!-- border-input-disabled -->
    <color name="color_border_input_readonly">#6CFF7B73</color> <!-- border-input-readonly -->
    <color name="color_border_input_danger">#03FFBA22</color> <!-- border-input-danger -->
    <color name="color_border_link">#9BFF355D</color> <!-- border-link -->
    <color name="color_border_success">#66FF8FB2</color> <!-- border-success -->
    <color name="color_border_warning">#1EFFC2AC</color> <!-- border-warning -->
    <color name="color_border_information">#E6FF7CA6</color> <!-- border-information -->
    <color name="color_border_danger">#5BFFFE77</color> <!-- border-danger -->
    <color name="color_border_button_hover">#40FF4E46</color> <!-- border-button-hover -->
    <color name="color_border_button_active">#40FF4E46</color> <!-- border-button-active -->
    <color name="color_border_neutral">#9CFFABA3</color> <!-- border-neutral -->
    <color name="color_border_link_hover">#49FF001C</color> <!-- border-link-hover -->
    <color name="color_border_link_neutral">#1AFF241E</color> <!-- border-link-neutral -->
    <color name="color_border_link_neutral_hover">#56FF645C</color> <!-- border-link-neutral-hover -->
    <color name="color_border_default_selected">#40FF4E46</color> <!-- border-default-selected -->
    <color name="color_data_data_4">#B1FF9A7F</color> <!-- data-data-4 -->
    <color name="color_data_data_4_subtle">#FAFFE4CC</color> <!-- data-data-4-subtle -->
    <color name="color_data_data_4_border">#67FF533B</color> <!-- data-data-4-border -->
    <color name="color_data_data_5">#39FFE957</color> <!-- data-data-5 -->
    <color name="color_data_data_5_subtle">#AFFFFFBC</color> <!-- data-data-5-subtle -->
    <color name="color_data_data_5_border">#01FF941A</color> <!-- data-data-5-border -->
    <color name="color_data_data_6">#06FFD287</color> <!-- data-data-6 -->
    <color name="color_data_data_6_subtle">#81FFFFD1</color> <!-- data-data-6-subtle -->
    <color name="color_data_data_6_border">#02FF8857</color> <!-- data-data-6-border -->
    <color name="color_data_data_7">#00FF9985</color> <!-- data-data-7 -->
    <color name="color_data_data_7_subtle">#97FFF5E9</color> <!-- data-data-7-subtle -->
    <color name="color_data_data_7_border">#00FF5348</color> <!-- data-data-7-border -->
    <color name="color_data_data_3_subtle">#FDFFC1DF</color> <!-- data-data-3-subtle -->
    <color name="color_data_data_3">#CEFF638D</color> <!-- data-data-3 -->
    <color name="color_data_data_8">#4BFF7699</color> <!-- data-data-8 -->
    <color name="color_data_data_2_subtle">#E2FFC0DE</color> <!-- data-data-2-subtle -->
    <color name="color_data_data_1">#84FF938A</color> <!-- data-data-1 -->
    <color name="color_data_data_1_border">#40FF4E46</color> <!-- data-data-1-border -->
    <color name="color_data_data_8_subtle">#A0FFC4E5</color> <!-- data-data-8-subtle -->
    <color name="color_data_data_8_border">#00FF3452</color> <!-- data-data-8-border -->
    <color name="color_data_data_3_border">#80FF2146</color> <!-- data-data-3-border -->
    <color name="color_data_data_2_border">#52FF2F4E</color> <!-- data-data-2-border -->
    <color name="color_data_data_1_subtle">#D0FFDED6</color> <!-- data-data-1-subtle -->
    <color name="color_data_data_2">#98FF7193</color> <!-- data-data-2 -->
    <color name="none">#00000000</color> <!-- Transparent -->
</resources>
